assignments/verilog_assign_2/full_adder.v
/*14.1-Bit Full Adder Using Gates
Write structural code using xor, and, or gates for a full adder.*/
module full_adder(
input a,b,cin,
output sum,carry);
wire w1,w2,w3;
//sum
xor g1(sum,a,b,cin);
//carry
and g2(w1,a,b);
and g3(w2,b,cin);
and g4(w3,a,cin);
or g5(carry,w2,w3,w1);
endmodule

assignments/verilog_assign_2/tb_full_adder.v
module tb_full_adder;
reg a,b,cin;
wire sum,carry;
full_adder dut (.a(a), .b(b), .cin(cin), .sum(sum), .carry(carry));
initial begin
$dumpfile("full_adder.vcd");
$dumpvars(0,tb_full_adder);
$monitor("Time=%0t | a=%b | b=%b | cin=%b | sum=%b | carry=%b",$time,a,b,cin,sum,carry);
a=0; b=0; cin=0; 
#5;a=0; b=0; cin=1;
#5;a=0; b=1; cin=0;
#5;a=0; b=1; cin=1;
#5;a=1; b=0; cin=0;
#5;a=1; b=0; cin=1;
#5;a=1; b=1; cin=0;
#5;a=1; b=1; cin=1;
$finish;
end
endmodule

assignments/verilog_assign_2/full_adder.vcd
$date
	Fri Sep  5 10:32:46 2025
$end
$version
	Icarus Verilog
$end
$timescale
	1s
$end
$scope module tb_full_adder $end
$var wire 1 ! sum $end
$var wire 1 " carry $end
$var reg 1 # a $end
$var reg 1 $ b $end
$var reg 1 % cin $end
$scope module dut $end
$var wire 1 # a $end
$var wire 1 $ b $end
$var wire 1 " carry $end
$var wire 1 % cin $end
$var wire 1 ! sum $end
$var wire 1 & w1 $end
$var wire 1 ' w2 $end
$var wire 1 ( w3 $end
$upscope $end
$upscope $end
$enddefinitions $end
$comment Show the parameter values. $end
$dumpall
$end
#0
$dumpvars
0(
0'
0&
0%
0$
0#
0"
0!
$end
#5
1!
1%
#10
0%
1$
#15
1"
0!
1'
1%
#20
0"
0'
1!
0%
0$
1#
#25
1"
0!
1(
1%
#30
0(
1&
0%
1$
#35
1!
1'
1(
1%
