assignments/verilog_assign_2/tri_mux.v
/*16.Tristate 2:1 MUX
Use bufif0 and bufif1 to design and test.*/
module tri_mux(i0,i1,s,y);
input i0,i1,s;
output y;
bufif0 (y,i0,s);
bufif1 (y,i1,s);
endmodule

assignments/verilog_assign_2/tb_tri_mux.v
module tb_tri_mux;
reg i0,i1,s;
wire y;
tri_mux dut (.i0(i0), .i1(i1), .s(s), .y(y));
initial begin
$dumpfile("ripple.vcd");
$dumpvars(0,tb_tri_mux);
$monitor("time=%0t| i0=%b | i1=%b | s=%b | y=%b",$time,i0,i1,s,y);
i0=0; i1=0; s=0; #5;
i0=0; i1=0; s=1; #5;
i0=0; i1=1; s=0; #5;
i0=0; i1=1; s=1; #5;
i0=1; i1=0; s=0; #5;
i0=1; i1=0; s=1; #5;
i0=1; i1=1; s=0; #5;
i0=1; i1=1; s=1; #5;
$finish;
end
endmodule

assignments/verilog_assign_2/ripple.vcd
$date
	Sun Sep  7 11:50:49 2025
$end
$version
	Icarus Verilog
$end
$timescale
	1s
$end
$scope module tb_tri_mux $end
$var wire 1 ! y $end
$var reg 1 " i0 $end
$var reg 1 # i1 $end
$var reg 1 $ s $end
$scope module dut $end
$var wire 1 " i0 $end
$var wire 1 # i1 $end
$var wire 1 $ s $end
$var wire 1 ! y $end
$upscope $end
$upscope $end
$enddefinitions $end
$comment Show the parameter values. $end
$dumpall
$end
#0
$dumpvars
0$
0#
0"
0!
$end
#5
1$
#10
0$
0!
1#
#15
1!
1$
#20
0$
1!
0#
1"
#25
0!
1$
#30
0$
1!
1#
#35
1$
