Day_2/full_sub/full_sub.v
module full_sub(a,bin,c,diff,bor);
input a,bin,c;
output diff, bor;
assign diff = a^bin^c;
assign bor = (~a&bin)|(bin&c)|(~a&c);
endmodule

Day_2/full_sub/tb_full_sub.v
module tb_full_sub;
reg a,bin,c;
wire diff,bor;
full_sub dut (.a(a), .bin(bin), .c(c), .diff(diff), .bor(bor));
initial begin
$dumpfile("full_sub.vcd");
$dumpvars(0,tb_full_sub);
$monitor("Time=%0t | a=%b | bin=%b | c=%b | diff=%b | bor=%b",$time,a,bin,c,diff,bor);
a=0; bin=0; c=0; #5;
a=0; bin=0; c=1; #5;
a=0; bin=1; c=0; #5;
a=0; bin=1; c=1; #5;
a=1; bin=0; c=0; #5;
a=1; bin=0; c=1; #5;
a=1; bin=1; c=0; #5;
a=1; bin=1; c=1; #5;
$finish;
end
endmodule

Day_2/full_sub/full_sub.vcd
$date
	Fri Sep  5 12:53:09 2025
$end
$version
	Icarus Verilog
$end
$timescale
	1s
$end
$scope module tb_full_sub $end
$var wire 1 ! diff $end
$var wire 1 " bor $end
$var reg 1 # a $end
$var reg 1 $ bin $end
$var reg 1 % c $end
$scope module dut $end
$var wire 1 # a $end
$var wire 1 $ bin $end
$var wire 1 " bor $end
$var wire 1 % c $end
$var wire 1 ! diff $end
$upscope $end
$upscope $end
$enddefinitions $end
$comment Show the parameter values. $end
$dumpall
$end
#0
$dumpvars
0%
0$
0#
0"
0!
$end
#5
1"
1!
1%
#10
0%
1$
#15
0!
1%
#20
0"
1!
0%
0$
1#
#25
0!
1%
#30
0%
1$
#35
1"
1!
1%
