assignments/verilog_assign_5/block_non_b/race.v
module race(input clk, input d, output reg x, output reg y);
    always @(posedge clk) begin
        x <= d;    // schedules update
        y <= x;    // uses OLD x, not new
    end
endmodule

assignments/tb_race.v
module tb_race;
    reg clk, d;
    wire x,y;

    race dut (.clk(clk), .d(d), .x(x), .y(y));
  
    initial clk=0;
    always #5 clk = ~clk;
 
    initial begin
            $dumpfile("race.vcd");
	    $dumpvars;
     	    $monitor("t=%0t | d=%b | Race: x=%b y=%b ",$time, d, x, y);

        d=0; #10;
        d=1; #10;
        d=0; #10;
        d=1; #10;
        #10 $finish;
    end
endmodule

assignments/verilog_assign_5/block_non_b/race.vcd
$date
	Thu Sep 11 10:51:43 2025
$end
$version
	Icarus Verilog
$end
$timescale
	1s
$end
$scope module tb_race $end
$var wire 1 ! y $end
$var wire 1 " x $end
$var reg 1 # clk $end
$var reg 1 $ d $end
$scope module dut $end
$var wire 1 # clk $end
$var wire 1 $ d $end
$var reg 1 " x $end
$var reg 1 ! y $end
$upscope $end
$upscope $end
$enddefinitions $end
$comment Show the parameter values. $end
$dumpall
$end
#0
$dumpvars
0$
0#
x"
x!
$end
#5
0"
1#
#10
0#
1$
#15
0!
1"
1#
#20
0#
0$
#25
1!
0"
1#
#30
0#
1$
#35
0!
1"
1#
#40
0#
#45
1!
1#
