Day_2/mux/mux.v
module mux(s,d0,d1,y);
input s;
input d0,d1;
output y;
assign y = ((~s)&d0) | (s&d1);
endmodule

Day_2/mux/tb_mux.v
module tb_mux;
reg s,d0,d1;
wire y;
mux dut (.s(s), .d0(d0), .d1(d1), .y(y));
initial begin
$dumpfile("mux.vcd");
$dumpvars(0,tb_mux);
$monitor("Time=%0t | s=%b | d0=%b | d1=%b | y=%b",$time,s,d0,d1,y);
s=0; d0=0; d1=0; #5;
s=0; d0=0; d1=1; #5;
s=0; d0=1; d1=0; #5;
s=0; d0=1; d1=1; #5;
s=1; d0=0; d1=0; #5;
s=1; d0=0; d1=1; #5;
s=1; d0=1; d1=0; #5;
s=1; d0=1; d1=1; #5;
$finish;
end
endmodule

Day_2/mux/mux.vcd
$date
	Fri Sep  5 18:13:07 2025
$end
$version
	Icarus Verilog
$end
$timescale
	1s
$end
$scope module tb_mux $end
$var wire 1 ! y $end
$var reg 1 " d0 $end
$var reg 1 # d1 $end
$var reg 1 $ s $end
$scope module dut $end
$var wire 1 " d0 $end
$var wire 1 # d1 $end
$var wire 1 $ s $end
$var wire 1 ! y $end
$upscope $end
$upscope $end
$enddefinitions $end
$comment Show the parameter values. $end
$dumpall
$end
#0
$dumpvars
0$
0#
0"
0!
$end
#5
1#
#10
1!
0#
1"
#15
1#
#20
0!
0#
0"
1$
#25
1!
1#
#30
0!
0#
1"
#35
1!
1#
